jinja2_django_compat/__init__.py
jinja2_django_compat/ext.py
jinja2_django_compat/functions.py
jinja2_django_compat-0.1.0.dist-info/DESCRIPTION.rst
jinja2_django_compat-0.1.0.dist-info/METADATA
jinja2_django_compat-0.1.0.dist-info/RECORD
jinja2_django_compat-0.1.0.dist-info/WHEEL
jinja2_django_compat-0.1.0.dist-info/metadata.json
jinja2_django_compat-0.1.0.dist-info/top_level.txt
